video_indexer/__init__.py
video_indexer/main.py
video_indexer-0.1.8.dist-info/LICENSE
video_indexer-0.1.8.dist-info/METADATA
video_indexer-0.1.8.dist-info/WHEEL
video_indexer-0.1.8.dist-info/top_level.txt
video_indexer-0.1.8.dist-info/RECORD
