Metadata-Version: 2.1
Name: video-indexer
Version: 0.1.8
Summary: Common function to query Microsoft Video Indexer
Home-page: https://github.com/bklim5/python_video_indexer_lib
Author: BK Lim
Author-email: bklim5@hotmail.com
License: MIT
Platform: UNKNOWN
Classifier: Programming Language :: Python :: 3
Classifier: License :: OSI Approved :: MIT License
Classifier: Operating System :: OS Independent
Requires-Dist: requests
